CHANGES.txt
README.txt
bootstrap.py
buildout.cfg
setup.py
src/zope/__init__.py
src/zope.app.i18nfile.egg-info/PKG-INFO
src/zope.app.i18nfile.egg-info/SOURCES.txt
src/zope.app.i18nfile.egg-info/dependency_links.txt
src/zope.app.i18nfile.egg-info/namespace_packages.txt
src/zope.app.i18nfile.egg-info/not-zip-safe
src/zope.app.i18nfile.egg-info/requires.txt
src/zope.app.i18nfile.egg-info/top_level.txt
src/zope/app/__init__.py
src/zope/app/i18nfile/DEPENDENCIES.cfg
src/zope/app/i18nfile/SETUP.cfg
src/zope/app/i18nfile/__init__.py
src/zope/app/i18nfile/configure.zcml
src/zope/app/i18nfile/ftesting.zcml
src/zope/app/i18nfile/i18nfile-configure.zcml
src/zope/app/i18nfile/i18nfile.py
src/zope/app/i18nfile/i18nimage.py
src/zope/app/i18nfile/interfaces.py
src/zope/app/i18nfile/testing.py
src/zope/app/i18nfile/browser/__init__.py
src/zope/app/i18nfile/browser/configure.zcml
src/zope/app/i18nfile/browser/file_edit.pt
src/zope/app/i18nfile/browser/i18nfile.py
src/zope/app/i18nfile/browser/i18nfile.txt
src/zope/app/i18nfile/browser/i18nimage.py
src/zope/app/i18nfile/browser/i18nimage.txt
src/zope/app/i18nfile/browser/image_edit.pt
src/zope/app/i18nfile/browser/tests.py
src/zope/app/i18nfile/tests/__init__.py
src/zope/app/i18nfile/tests/test_i18nfile.py
src/zope/app/i18nfile/tests/test_i18nimage.py
