Metadata-Version: 1.0
Name: zope.app.i18nfile
Version: 3.4.1
Summary: I18n File and Image -- Zope 3 Content Components
Home-page: http://cheeseshop.python.org/pypi/zope.app.i18nfile
Author: Zope Corporation and Contributors
Author-email: zope3-dev@zope.org
License: ZPL 2.1
Keywords: zope3 i18n l10n file image content
Platform: UNKNOWN
Classifier: Development Status :: 5 - Production/Stable
Classifier: Environment :: Web Environment
Classifier: Intended Audience :: Developers
Classifier: License :: OSI Approved :: Zope Public License
Classifier: Programming Language :: Python
Classifier: Natural Language :: English
Classifier: Operating System :: OS Independent
Classifier: Topic :: Internet :: WWW/HTTP
Classifier: Framework :: Zope3
